{
    "versionLabel": "1.0.0",
    "uuid": "25a9793b-3c40-4f38-8144-5fe49a2f6ddf",
    "appKeys": {
        "action": 1,
        "hash": 2,
        "value": 3
    },
    "longName": "uTorrent Remote",
    "versionCode": 1,
    "capabilities": [
        "configurable"
    ],
    "shortName": "uTorrent",
    "companyName": "jjv360",
    "watchapp": {
        "watchface": false
    },
    "resources": {
        "media": [
            {
                "type": "png",
                "name": "STOP_ICON",
                "file": "images/Stopped.png"
            },
            {
                "type": "png",
                "name": "COMPLETE_ICON",
                "file": "images/Complete.png"
            },
            {
                "type": "png",
                "name": "DOWNLOAD_ICON",
                "file": "images/Downloading.png"
            },
            {
                "type": "png",
                "name": "IMAGE_BIG_ICON",
                "file": "images/Big Icon.png"
            },
            {
                "menuIcon": true,
                "type": "png",
                "name": "IMAGE_MAIN_ICON",
                "file": "images/uTorrent Main Icon.png"
            }
        ]
    }
}
